Workbook

Sheet Assumptions
A1: PERSONAL BUDDIES - pricing assumptions (CAD)
A3: Filament per unit | B3: 3.8
A4: Print time (hours) | B4: 6
A5: Print cost per hour | B5: 2.5
A6: Assembly/test labour (hours) | B6: 1
A7: Labour rate per hour | B7: 25
A8: Packaging per unit | B8: 5
A9: Stripe fee pct | B9: 0.029
A10: Stripe fee fixed | B10: 0.3
A11: Warranty reserve pct | B11: 0.03
A12: Rework reserve pct | B12: 0.03
A13: Change any B value and the Tier pricing sheet recalculates. | B13: 0.5

Sheet Tier pricing
A1: Tier | B1: Parts (CAD) | C1: Fixed unit cost | D1: Proposed price (CAD) | E1: Variable fees | F1: Total cost | G1: Gross margin | H1: Meets 50% target?
A2: Starter | B2: 56.72 | C2: =B2+Assumptions!$B$3+Assumptions!$B$4*Assumptions!$B$5+Assumptions!$B$6*Assumptions!$B$7+Assumptions!$B$8 | D2: 259 | E2: =D2*Assumptions!$B$9+Assumptions!$B$10+D2*Assumptions!$B$11+D2*Assumptions!$B$12 | F2: =C2+E2 | G2: =(D2-F2)/D2 | H2: =IF(G2>=Assumptions!$B$13,"YES","NO")
A3: Smart | B3: 68.74 | C3: =B3+Assumptions!$B$3+Assumptions!$B$4*Assumptions!$B$5+Assumptions!$B$6*Assumptions!$B$7+Assumptions!$B$8 | D3: 289 | E3: =D3*Assumptions!$B$9+Assumptions!$B$10+D3*Assumptions!$B$11+D3*Assumptions!$B$12 | F3: =C3+E3 | G3: =(D3-F3)/D3 | H3: =IF(G3>=Assumptions!$B$13,"YES","NO")
A4: Premium | B4: 87.83 | C4: =B4+Assumptions!$B$3+Assumptions!$B$4*Assumptions!$B$5+Assumptions!$B$6*Assumptions!$B$7+Assumptions!$B$8 | D4: 335 | E4: =D4*Assumptions!$B$9+Assumptions!$B$10+D4*Assumptions!$B$11+D4*Assumptions!$B$12 | F4: =C4+E4 | G4: =(D4-F4)/D4 | H4: =IF(G4>=Assumptions!$B$13,"YES","NO")
A5: Custom (floor) | B5: 87.83 | C5: =B5+Assumptions!$B$3+Assumptions!$B$4*Assumptions!$B$5+Assumptions!$B$6*Assumptions!$B$7+Assumptions!$B$8 | D5: 399 | E5: =D5*Assumptions!$B$9+Assumptions!$B$10+D5*Assumptions!$B$11+D5*Assumptions!$B$12 | F5: =C5+E5 | G5: =(D5-F5)/D5 | H5: =IF(G5>=Assumptions!$B$13,"YES","NO")
A6: Voice (SD boot) | B6: 378.65 | C6: =B6+Assumptions!$B$3+Assumptions!$B$4*Assumptions!$B$5+Assumptions!$B$6*Assumptions!$B$7+Assumptions!$B$8 | D6: 1049 | E6: =D6*Assumptions!$B$9+Assumptions!$B$10+D6*Assumptions!$B$11+D6*Assumptions!$B$12 | F6: =C6+E6 | G6: =(D6-F6)/D6 | H6: =IF(G6>=Assumptions!$B$13,"YES","NO")
A7: Voice (NVMe) | B7: 456.75 | C7: =B7+Assumptions!$B$3+Assumptions!$B$4*Assumptions!$B$5+Assumptions!$B$6*Assumptions!$B$7+Assumptions!$B$8 | D7: 1239 | E7: =D7*Assumptions!$B$9+Assumptions!$B$10+D7*Assumptions!$B$11+D7*Assumptions!$B$12 | F7: =C7+E7 | G7: =(D7-F7)/D7 | H7: =IF(G7>=Assumptions!$B$13,"YES","NO")
A9: Custom tier: fixed cost excludes design labour; quote must cover it.
A10: Voice tier: Pi 5 prices are volatile; review monthly and confirm price at order.

Sheet BOM
A1: tier | B1: part | C1: spec | D1: supplier | E1: unit_price_cad | F1: qty | G1: line_total | H1: source_url | I1: checked_date
A2: starter | B2: ESP32-S3 dev board | C2: ESP32-S3-DevKitC-1 N16R8, Type-C [UNVERIFIED: catalog snapshot only, page blocked] | D2: Walmart.ca (marketplace seller) | E2: 16.65 | F2: 1 | G2: 16.65 | H2: https://www.walmart.ca/en/ip/ESP32-S3-DevKitC-1-Development-Board-Module-Equipped-with-the-ESP32-S3-1-N16R8-Module-WIFI-No-Welding-1-Development-Board-Module/3GYRLZQ78NVB | I2: 2026-10-18
A3: starter | B3: OLED display 0.96in | C3: SSD1306 128x64 I2C, blue, presoldered pins [GBP->CAD approx @1.83] | D3: AdditiveArcade (UK) | E3: 6.68 | F3: 1 | G3: 6.68 | H3: https://additivearcade.com/products/096-oled-display | I3: 2026-10-18
A4: starter | B4: DS3231 RTC module | C4: with AT24C32 EEPROM, CR2032 battery included [USD->CAD @1.4125] | D4: Addicore (US) | E4: 6.48 | F4: 1 | G4: 6.48 | H4: https://www.addicore.com/products/ds3231-real-time-clock-module-with-eeprom | I4: 2026-10-18
A5: starter | B5: Piezo buzzer module | C5: active 5V, 22x22mm PCB [USD->CAD @1.4125] | D5: HackMakeMod (US) | E5: 4.22 | F5: 1 | G5: 4.22 | H5: https://hackmakemod.com/products/active-buzzer | I5: 2026-10-18
A6: starter | B6: Tactile push button | C6: 6x6x4.3mm momentary [USD->CAD @1.4125] | D6: SaberBay (US) | E6: 1.41 | F6: 2 | G6: 2.82 | H6: https://www.saberbay.com/products/untitled-sep6_08-10 | I6: 2026-10-18
A7: starter | B7: USB-C breakout | C7: panel-mount breakout + cable [USD->CAD @1.4125; NOTE: fightstick form factor, re-source a generic PCB breakout] | D7: EternalRival (US) | E7: 9.87 | F7: 1 | G7: 9.87 | H7: https://www.eternalrival.com/products/usb-c-low-profile-bracket-with-cable | I7: 2026-10-18
A8: starter | B8: USB-C cable 1m | C8: generic charge cable [UNVERIFIED estimate] | D8: n/a | E8: 10.00 | F8: 1 | G8: 10.00 | I8: 2026-10-18
A9: smart | B9: SHT40 temp/humidity module | C9: I2C module [UNVERIFIED; reference Adafruit 4885 $5.95 USD -> CAD @1.4125] | D9: n/a | E9: 8.40 | F9: 1 | G9: 8.40 | H9: https://www.adafruit.com/product/4885 | I9: 2026-10-18
A10: smart | B10: WS2812B RGB LEDs | C10: 15-LED segment from 60 LED/m strip, 5V [USD->CAD @1.4125, pro-rata] | D10: ShillehTek (US) | E10: 2.12 | F10: 1 | G10: 2.12 | H10: https://shillehtek.com/products/non-waterproof-ws2812b-smd-led-strip-60-led-meter-flexible-5m-roll-5v-ip30 | I10: 2026-10-18
A11: smart | B11: RGB diffuser | C11: frosted strip for LED diffuser [UNVERIFIED estimate] | D11: n/a | E11: 1.50 | F11: 1 | G11: 1.50 | I11: 2026-10-18
A12: premium | B12: TTP223 touch module | C12: capacitive touch, 3.3-5V [GBP->CAD approx @1.83] | D12: Switch Electronics (UK) | E12: 1.88 | F12: 1 | G12: 1.88 | H12: https://www.switchelectronics.co.uk/products/ttp223b-1-channel-capacitive-touch-button-switch-module | I12: 2026-10-18
A13: premium | B13: MAX98357A I2S amp | C13: I2S 3W Class-D breakout [USD->CAD @1.4125] | D13: PMD Way (AU) | E13: 13.02 | F13: 1 | G13: 13.02 | H13: https://pmdway.com/products/max98357-i2s-3w-class-d-amplifier-breakout | I13: 2026-10-18
A14: premium | B14: Speaker | C14: 8 ohm 2W, 40mm [USD->CAD @1.4125] | D14: ameriDroid (US) | E14: 4.17 | F14: 1 | G14: 4.17 | H14: https://ameridroid.com/products/8ohm-2w-36mm-mini-speaker | I14: 2026-10-18
A15: voice | B15: Raspberry Pi 5 8GB | C15: SC1112 board, 8GB LPDDR4X | D15: PiShop.ca | E15: 249.50 | F15: 1 | G15: 249.50 | H15: https://www.pishop.ca/product/raspberry-pi-5-8gb/ | I15: 2026-10-18
A16: voice | B16: Raspberry Pi 5 16GB | C16: SC1113 board, 16GB [listed for reference; NOT recommended - RAM unused by workload] | D16: PiShop.ca | E16: 434.85 | F16: 1 | G16: 434.85 | H16: https://www.pishop.ca/product/raspberry-pi-5-16gb/ | I16: 2026-10-18
A17: voice | B17: Pi 5 Active Cooler | C17: official SC1148 | D17: PiShop.ca | E17: 7.15 | F17: 1 | G17: 7.15 | H17: https://www.pishop.ca/product/raspberry-pi-active-cooler/ | I17: 2026-10-18
A18: voice | B18: USB microphone | C18: Adafruit mini USB mic [NOTE: not a mic array; ReSpeaker array UNVERIFIED at CA reseller] | D18: PiShop.ca | E18: 8.95 | F18: 1 | G18: 8.95 | H18: https://www.pishop.ca/product/mini-usb-microphone/ | I18: 2026-10-18
A19: voice | B19: Round IPS display | C19: Waveshare 1.28in 240x240 IPS GC9A01, 4-wire SPI | D19: PiShop.ca | E19: 20.95 | F19: 1 | G19: 20.95 | H19: https://www.pishop.ca/product/240x240-general-1-28inch-round-lcd-display-module-65k-rgb/ | I19: 2026-10-18
A20: voice | B20: microSD 128GB | C20: SanDisk High Endurance, UHS-I | D20: PiShop.ca | E20: 55.45 | F20: 1 | G20: 55.45 | H20: https://www.pishop.ca/product/sandisk-128gb-high-endurance-microsdxc-card-blank/ | I20: 2026-10-18
A21: voice | B21: 27W USB-C PD PSU | C21: official 5.1V/5A PD, white US | D21: PiShop.ca | E21: 16.95 | F21: 1 | G21: 16.95 | H21: https://www.pishop.ca/product/raspberry-pi-27w-usb-c-power-supply-white-us/ | I21: 2026-10-18
A22: voice | B22: Mute slide switch | C22: DPDT on-on, 2-pack at CA$5.01 -> per-unit | D22: B&E Electronics (Calgary) | E22: 2.51 | F22: 1 | G22: 2.51 | H22: https://be-electronics.com/products/mode-46-010-2-slide-switch-dpdt-on-on-3a-125vac-1-5a-250vac-solder-terminals-2-pack | I22: 2026-10-18
A23: voice | B23: MAX98357A I2S amp | C23: I2S 3W Class-D breakout [USD->CAD @1.4125] | D23: PMD Way (AU) | E23: 13.02 | F23: 1 | G23: 13.02 | H23: https://pmdway.com/products/max98357-i2s-3w-class-d-amplifier-breakout | I23: 2026-10-18
... A25: voice | B25: NVMe HAT (optional) | C25: Waveshare PCIe-to-M.2 board (D), 2230-2280 | D25: PiShop.ca | E25: 10.60 | F25: 1 | G25: 10.60 | H25: https://www.pishop.ca/product/pcie-to-m-2-adapter-board-d-for-raspberry-pi-5/ | I25: 2026-10-18
A26: voice | B26: NVMe SSD 256GB (optional) | C26: budget 256GB [UNVERIFIED current price; PiShop 256GB SSDs all OOS today] | D26: Amazon.ca | E26: 67.50 | F26: 1 | G26: 67.50 | I26: 2026-10-18
A27: custom | B27: OLED display 1.3in | C27: SH1106 128x64 I2C, white [USD->CAD @1.4125; upgrade option] | D27: ShillehTek (US) | E27: 12.70 | F27: 1 | G27: 12.70 | H27: https://shillehtek.com/products/1-3-i2c-white-oled-display-module-4-pin-sh1106 | I27: 2026-10-18
A28: all | B28: PLA filament | C28: Elegoo PLA 1kg, ~200g per buddy | D28: Elegoo CA (ca.elegoo.com) | E28: 18.99 | F28: 0.2 | G28: 3.80 | H28: https://ca.elegoo.com/products/pla-filament-1-75mm-colored-1kg | I28: 2026-10-18
A29: all | B29: Machine time | C29: ~6 print-hours @ CA$2.50/h all-in (depreciation + wear + power) [ESTIMATE] | D29: n/a | E29: 15.00 | F29: 1 | G29: 15.00 | I29: 2026-10-18
A30: all | B30: Assembly + test labour | C30: 60 min @ CA$25/h, Halifax [ASSUMPTION - validate with timed builds] | D30: n/a | E30: 25.00 | F30: 1 | G30: 25.00 | I30: 2026-10-18
A31: all | B31: Packaging | C31: box + padding + insert [ESTIMATE] | D31: n/a | E31: 5.00 | F31: 1 | G31: 5.00 | I31: 2026-10-18

Sheet Add-ons
A1: Add-on | B1: Price (CAD) | C1: Est. cost | D1: Margin
A2: Extra / two-tone colour | B2: 12 | C2: 4 | D2: =(B2-C2)/B2
A3: 1.3" OLED upgrade | B3: 15 | C3: 6 | D3: =(B3-C3)/B3
A4: Custom message pack | B4: 15 | C4: 2 | D4: =(B4-C4)/B4
A5: Gift wrap | B5: 12 | C5: 4 | D5: =(B5-C5)/B5
A6: Spare parts kit | B6: 18 | C6: 7 | D6: =(B6-C6)/B6
A7: Certified 5V/3A PSU | B7: 18 | C7: 9 | D7: =(B7-C7)/B7
A8: Extra USB-C cable | B8: 12 | C8: 5 | D8: =(B8-C8)/B8
A9: Second-year extended warranty | B9: 25 | C9: 8 | D9: =(B9-C9)/B9
